easy_detection/__init__.py
easy_detection/centerface.onnx
easy_detection/centerface800_480.onnx
easy_detection/detection.py
easy_detection/test.jpg
easy_detection-1.0.2.dist-info/LICENSE
easy_detection-1.0.2.dist-info/METADATA
easy_detection-1.0.2.dist-info/WHEEL
easy_detection-1.0.2.dist-info/top_level.txt
easy_detection-1.0.2.dist-info/RECORD
